meerk40t/__init__.py
meerk40t/constants.py
meerk40t/external_plugins.py
meerk40t/external_plugins_build.py
meerk40t/internal_plugins.py
meerk40t/main.py
meerk40t/svgelements.py
meerk40t/balormk/__init__.py
meerk40t/balormk/balor_params.py
meerk40t/balormk/clone_loader.py
meerk40t/balormk/controller.py
meerk40t/balormk/cylindermod.py
meerk40t/balormk/device.py
meerk40t/balormk/driver.py
meerk40t/balormk/galvo_commands.py
meerk40t/balormk/livelightjob.py
meerk40t/balormk/mock_connection.py
meerk40t/balormk/plugin.py
meerk40t/balormk/usb_connection.py
meerk40t/balormk/gui/__init__.py
meerk40t/balormk/gui/balorconfig.py
meerk40t/balormk/gui/balorcontroller.py
meerk40t/balormk/gui/baloroperationproperties.py
meerk40t/balormk/gui/corscene.py
meerk40t/balormk/gui/gui.py
meerk40t/camera/__init__.py
meerk40t/camera/camera.py
meerk40t/camera/plugin.py
meerk40t/camera/gui/__init__.py
meerk40t/camera/gui/camerapanel.py
meerk40t/camera/gui/gui.py
meerk40t/ch341/__init__.py
meerk40t/ch341/ch341device.py
meerk40t/ch341/libusb.py
meerk40t/ch341/mock.py
meerk40t/ch341/windriver.py
meerk40t/core/__init__.py
meerk40t/core/bindalias.py
meerk40t/core/core.py
meerk40t/core/cutplan.py
meerk40t/core/drivers.py
meerk40t/core/exceptions.py
meerk40t/core/geomstr.py
meerk40t/core/laserjob.py
meerk40t/core/logging.py
meerk40t/core/parameters.py
meerk40t/core/planner.py
meerk40t/core/plotplanner.py
meerk40t/core/space.py
meerk40t/core/spoolers.py
meerk40t/core/svg_io.py
meerk40t/core/treeop.py
meerk40t/core/undos.py
meerk40t/core/units.py
meerk40t/core/view.py
meerk40t/core/webhelp.py
meerk40t/core/wordlist.py
meerk40t/core/cutcode/__init__.py
meerk40t/core/cutcode/cubiccut.py
meerk40t/core/cutcode/cutcode.py
meerk40t/core/cutcode/cutgroup.py
meerk40t/core/cutcode/cutobject.py
meerk40t/core/cutcode/dwellcut.py
meerk40t/core/cutcode/gotocut.py
meerk40t/core/cutcode/homecut.py
meerk40t/core/cutcode/inputcut.py
meerk40t/core/cutcode/linecut.py
meerk40t/core/cutcode/outputcut.py
meerk40t-0.9.9000.dist-info/licenses/LICENSE
meerk40t-0.9.9000.dist-info/METADATA
meerk40t-0.9.9000.dist-info/WHEEL
meerk40t-0.9.9000.dist-info/entry_points.txt
meerk40t-0.9.9000.dist-info/top_level.txt
meerk40t-0.9.9000.dist-info/zip-safe
meerk40t-0.9.9000.dist-info/RECORD
