Metadata-Version: 2.4
Name: meerk40t
Version: 0.9.9000
Summary: MeerK40t LaserCutter Software
Home-page: https://github.com/meerk40t/meerk40t
Author: jpirnay
Author-email: jens@pirnay.com
License: MIT
Keywords: lasercutter,laser,vector,parser
Classifier: Development Status :: 5 - Production/Stable
Classifier: License :: OSI Approved :: MIT License
Classifier: Operating System :: OS Independent
Classifier: Programming Language :: Python
Classifier: Programming Language :: Python :: 3.6
Classifier: Programming Language :: Python :: 3.7
Classifier: Programming Language :: Python :: 3.8
Classifier: Programming Language :: Python :: 3.9
Classifier: Programming Language :: Python :: 3.10
Classifier: Topic :: Multimedia :: Graphics
Classifier: Topic :: Multimedia :: Graphics :: Editors :: Vector-Based
Classifier: Topic :: Utilities
License-File: LICENSE
Requires-Dist: pyusb>=1.0.0
Requires-Dist: pyserial
Requires-Dist: numpy
Provides-Extra: all
Requires-Dist: wxPython>=4.0.0; extra == "all"
Requires-Dist: Pillow>=7.0.0; extra == "all"
Requires-Dist: opencv-python-headless>=3.4.0.0; extra == "all"
Requires-Dist: ezdxf>=0.14.0; extra == "all"
Provides-Extra: gui
Requires-Dist: wxPython>=4.0.0; extra == "gui"
Requires-Dist: Pillow>=7.0.0; extra == "gui"
Provides-Extra: cam
Requires-Dist: opencv-python-headless>=3.4.0.0; extra == "cam"
Provides-Extra: dxf
Requires-Dist: ezdxf>=0.14.0; extra == "dxf"
Provides-Extra: camhead
Requires-Dist: opencv-python>=3.4.0.0; extra == "camhead"
Dynamic: license-file
Dynamic: provides-extra
Dynamic: requires-dist
